{
  "id": "crash-landing-ep10-12",
  "title": "A Deadly Escape and a Vow",
  "drama": "Crash Landing on You",
  "youtubeId": "xMHvBErDplE",
  "episode": 10,
  "part": 12,
  "introOffset": 0,
  "words": [
    {
      "korean": "놓치다",
      "romanization": "nochida",
      "english": "to miss; to let slip",
      "spanish": "perder; dejar escapar",
      "portuguese": "perder; deixar escapar",
      "indonesian": "melewatkan; kehilangan",
      "japanese": "逃す; 見落とす",
      "thai": "พลาด",
      "french": "manquer; laisser échapper",
      "chinese": "错过；漏掉",
      "chineseTraditional": "錯過；漏掉",
      "partOfSpeech": "verb",
      "emoji": "🫥",
      "example": "버스를 아슬아슬하게 놓쳤어요.",
      "exampleRomanization": "beoseureul aseuraseulhage nochyeosseoyo.",
      "exampleTranslation": "I just barely missed the bus.",
      "timestamp": 24.0
    },
    {
      "korean": "밀수",
      "romanization": "milsu",
      "english": "smuggling",
      "spanish": "contrabando",
      "portuguese": "contrabando",
      "indonesian": "penyelundupan",
      "japanese": "密輸",
      "thai": "การลักลอบ",
      "french": "contrebande",
      "chinese": "走私",
      "chineseTraditional": "走私",
      "partOfSpeech": "noun",
      "emoji": "🚢",
      "example": "그 배는 밀수로 적발됐어요.",
      "exampleRomanization": "geu baeneun milsuro jeokbaldwaesseoyo.",
      "exampleTranslation": "That ship was caught smuggling.",
      "timestamp": 32.0
    },
    {
      "korean": "강철",
      "romanization": "gangcheol",
      "english": "steel",
      "spanish": "acero",
      "portuguese": "aço",
      "indonesian": "baja",
      "japanese": "鋼鉄",
      "thai": "เหล็กกล้า",
      "french": "acier",
      "chinese": "钢铁",
      "chineseTraditional": "鋼鐵",
      "partOfSpeech": "noun",
      "emoji": "🔩",
      "example": "이 다리는 강철로 만들었어요.",
      "exampleRomanization": "i darineun gangcheollo mandeureosseoyo.",
      "exampleTranslation": "This bridge is made of steel.",
      "timestamp": 33.0
    },
    {
      "korean": "차이",
      "romanization": "chai",
      "english": "difference; gap",
      "spanish": "diferencia",
      "portuguese": "diferença",
      "indonesian": "perbedaan",
      "japanese": "違い; 差",
      "thai": "ความแตกต่าง",
      "french": "différence; écart",
      "chinese": "差异；差别",
      "chineseTraditional": "差異；差別",
      "partOfSpeech": "noun",
      "emoji": "↔️",
      "example": "두 제품의 가격 차이가 커요.",
      "exampleRomanization": "du jepumui gagyeok chaiga keoyo.",
      "exampleTranslation": "The price difference between the two products is big.",
      "timestamp": 45.0
    },
    {
      "korean": "달러",
      "romanization": "dalleo",
      "english": "dollar",
      "spanish": "dólar",
      "portuguese": "dólar",
      "indonesian": "dolar",
      "japanese": "ドル",
      "thai": "ดอลลาร์",
      "french": "dollar",
      "chinese": "美元",
      "chineseTraditional": "美元",
      "partOfSpeech": "noun",
      "emoji": "💵",
      "example": "환전소에서 달러로 바꿨어요.",
      "exampleRomanization": "hwanjeonsoeseo dalleoro bakkwosseoyo.",
      "exampleTranslation": "I exchanged it for dollars at the currency booth.",
      "timestamp": 58.48
    },
    {
      "korean": "제조",
      "romanization": "jejo",
      "english": "manufacture; production",
      "spanish": "fabricación",
      "portuguese": "fabricação",
      "indonesian": "pembuatan; produksi",
      "japanese": "製造",
      "thai": "การผลิต",
      "french": "fabrication",
      "chinese": "制造",
      "chineseTraditional": "製造",
      "partOfSpeech": "noun",
      "emoji": "🏭",
      "example": "이 약은 국내에서 제조돼요.",
      "exampleRomanization": "i yageun gungnaeeseo jejodwaeyo.",
      "exampleTranslation": "This medicine is manufactured domestically.",
      "timestamp": 63.08
    },
    {
      "korean": "목표",
      "romanization": "mokpyo",
      "english": "goal; target",
      "spanish": "objetivo; meta",
      "portuguese": "objetivo; meta",
      "indonesian": "tujuan; sasaran",
      "japanese": "目標",
      "thai": "เป้าหมาย",
      "french": "objectif; cible",
      "chinese": "目标",
      "chineseTraditional": "目標",
      "partOfSpeech": "noun",
      "emoji": "🎯",
      "example": "올해 목표는 책 열 권 읽기예요.",
      "exampleRomanization": "olhae mokpyoneun chaek yeol gwon ilkgiyeyo.",
      "exampleTranslation": "My goal this year is to read ten books.",
      "timestamp": 70.64
    },
    {
      "korean": "차량",
      "romanization": "charyang",
      "english": "vehicle",
      "spanish": "vehículo",
      "portuguese": "veículo",
      "indonesian": "kendaraan",
      "japanese": "車両",
      "thai": "ยานพาหนะ",
      "french": "véhicule",
      "chinese": "车辆",
      "chineseTraditional": "車輛",
      "partOfSpeech": "noun",
      "emoji": "🚙",
      "example": "이 도로는 차량이 많이 다녀요.",
      "exampleRomanization": "i doroneun charyangi mani danyeoyo.",
      "exampleTranslation": "Many vehicles pass along this road.",
      "timestamp": 73.5
    },
    {
      "korean": "번호",
      "romanization": "beonho",
      "english": "number",
      "spanish": "número",
      "portuguese": "número",
      "indonesian": "nomor",
      "japanese": "番号",
      "thai": "หมายเลข",
      "french": "numéro",
      "chinese": "号码",
      "chineseTraditional": "號碼",
      "partOfSpeech": "noun",
      "emoji": "🔢",
      "example": "전화번호를 다시 알려 주세요.",
      "exampleRomanization": "jeonhwabeonhoreul dasi allyeo juseyo.",
      "exampleTranslation": "Please tell me your phone number again.",
      "timestamp": 74.5
    },
    {
      "korean": "난리",
      "romanization": "nalli",
      "english": "commotion; chaos; fuss",
      "spanish": "alboroto; caos",
      "portuguese": "alvoroço; caos",
      "indonesian": "kekacauan; keributan",
      "japanese": "大騒ぎ",
      "thai": "ความวุ่นวาย",
      "french": "chaos; grand tapage",
      "chinese": "乱子；骚动",
      "chineseTraditional": "亂子；騷動",
      "partOfSpeech": "noun",
      "emoji": "🌪️",
      "example": "갑자기 정전이 돼서 난리가 났어요.",
      "exampleRomanization": "gapjagi jeongjeoni dwaeseo nalliga nasseoyo.",
      "exampleTranslation": "There was chaos when the power suddenly went out.",
      "timestamp": 108.76
    },
    {
      "korean": "의도적",
      "romanization": "uidojeok",
      "english": "intentional; deliberate",
      "spanish": "intencional; deliberado",
      "portuguese": "intencional; deliberado",
      "indonesian": "disengaja",
      "japanese": "意図的",
      "thai": "โดยเจตนา",
      "french": "intentionnel; délibéré",
      "chinese": "故意的",
      "chineseTraditional": "故意的",
      "partOfSpeech": "adjective",
      "emoji": "🎯",
      "example": "그건 의도적인 실수였어요.",
      "exampleRomanization": "geugeon uidojeogin silsuyeosseoyo.",
      "exampleTranslation": "That was a deliberate mistake.",
      "timestamp": 148.48
    },
    {
      "korean": "뇌물",
      "romanization": "noemul",
      "english": "bribe",
      "spanish": "soborno",
      "portuguese": "suborno",
      "indonesian": "suap",
      "japanese": "賄賂",
      "thai": "สินบน",
      "french": "pot-de-vin",
      "chinese": "贿赂",
      "chineseTraditional": "賄賂",
      "partOfSpeech": "noun",
      "emoji": "💸",
      "example": "그 관리는 뇌물을 받고 체포됐어요.",
      "exampleRomanization": "geu gwanrineun noemureul batgo chepodwaesseoyo.",
      "exampleTranslation": "That official was arrested for taking a bribe.",
      "timestamp": 152.1
    },
    {
      "korean": "간부",
      "romanization": "ganbu",
      "english": "executive; senior official",
      "spanish": "alto cargo; directivo",
      "portuguese": "dirigente; alto funcionário",
      "indonesian": "petinggi; pejabat senior",
      "japanese": "幹部",
      "thai": "ผู้บริหารระดับสูง",
      "french": "cadre; haut responsable",
      "chinese": "干部；高层",
      "chineseTraditional": "幹部；高層",
      "partOfSpeech": "noun",
      "emoji": "👔",
      "example": "회사 간부들이 회의에 모였어요.",
      "exampleRomanization": "hoesa ganbudeuri hoeuie moyeosseoyo.",
      "exampleTranslation": "The company executives gathered for the meeting.",
      "timestamp": 153.0
    },
    {
      "korean": "입",
      "romanization": "ip",
      "english": "mouth",
      "spanish": "boca",
      "portuguese": "boca",
      "indonesian": "mulut",
      "japanese": "口",
      "thai": "ปาก",
      "french": "bouche",
      "chinese": "嘴",
      "chineseTraditional": "嘴",
      "partOfSpeech": "noun",
      "emoji": "👄",
      "example": "그는 입이 무거운 사람이에요.",
      "exampleRomanization": "geuneun ibi mugeoun saramieyo.",
      "exampleTranslation": "He is a tight-lipped person.",
      "timestamp": 172.86
    },
    {
      "korean": "인원",
      "romanization": "inwon",
      "english": "number of people; personnel",
      "spanish": "número de personas; personal",
      "portuguese": "número de pessoas; efetivo",
      "indonesian": "jumlah orang; personel",
      "japanese": "人員",
      "thai": "จำนวนคน; บุคลากร",
      "french": "effectif; personnel",
      "chinese": "人员；人数",
      "chineseTraditional": "人員；人數",
      "partOfSpeech": "noun",
      "emoji": "👥",
      "example": "참석 인원이 생각보다 많았어요.",
      "exampleRomanization": "chamseok inwoni saenggakboda manasseoyo.",
      "exampleTranslation": "There were more attendees than expected.",
      "timestamp": 177.36
    },
    {
      "korean": "사상자",
      "romanization": "sasangja",
      "english": "casualties (dead and wounded)",
      "spanish": "víctimas; bajas",
      "portuguese": "vítimas; baixas",
      "indonesian": "korban jiwa dan luka",
      "japanese": "死傷者",
      "thai": "ผู้บาดเจ็บและเสียชีวิต",
      "french": "victimes; pertes",
      "chinese": "伤亡者",
      "chineseTraditional": "傷亡者",
      "partOfSpeech": "noun",
      "emoji": "🚑",
      "example": "다행히 사상자는 없었어요.",
      "exampleRomanization": "dahaenghi sasangjaneun eopseosseoyo.",
      "exampleTranslation": "Fortunately, there were no casualties.",
      "timestamp": 178.0
    },
    {
      "korean": "발견",
      "romanization": "balgyeon",
      "english": "discovery; finding",
      "spanish": "descubrimiento; hallazgo",
      "portuguese": "descoberta",
      "indonesian": "penemuan",
      "japanese": "発見",
      "thai": "การค้นพบ",
      "french": "découverte",
      "chinese": "发现",
      "chineseTraditional": "發現",
      "partOfSpeech": "noun",
      "emoji": "🔦",
      "example": "새로운 화석이 발견됐어요.",
      "exampleRomanization": "saeroun hwaseogi balgyeondwaesseoyo.",
      "exampleTranslation": "A new fossil was discovered.",
      "timestamp": 181.34
    },
    {
      "korean": "현장",
      "romanization": "hyeonjang",
      "english": "scene; site",
      "spanish": "lugar; escena",
      "portuguese": "local; cena",
      "indonesian": "lokasi; tempat kejadian",
      "japanese": "現場",
      "thai": "ที่เกิดเหตุ",
      "french": "lieu; scène",
      "chinese": "现场",
      "chineseTraditional": "現場",
      "partOfSpeech": "noun",
      "emoji": "📍",
      "example": "경찰이 현장을 조사하고 있어요.",
      "exampleRomanization": "gyeongchari hyeonjangeul josahago isseoyo.",
      "exampleTranslation": "The police are examining the scene.",
      "timestamp": 185.54
    },
    {
      "korean": "협조",
      "romanization": "hyeopjo",
      "english": "cooperation",
      "spanish": "cooperación; colaboración",
      "portuguese": "cooperação; colaboração",
      "indonesian": "kerja sama",
      "japanese": "協力",
      "thai": "ความร่วมมือ",
      "french": "coopération",
      "chinese": "协助；配合",
      "chineseTraditional": "協助；配合",
      "partOfSpeech": "noun",
      "emoji": "🤝",
      "example": "여러분의 협조에 감사드립니다.",
      "exampleRomanization": "yeoreobunui hyeopjoe gamsadeurimnida.",
      "exampleTranslation": "Thank you all for your cooperation.",
      "timestamp": 191.88
    },
    {
      "korean": "가능성",
      "romanization": "ganeungseong",
      "english": "possibility; likelihood",
      "spanish": "posibilidad",
      "portuguese": "possibilidade",
      "indonesian": "kemungkinan",
      "japanese": "可能性",
      "thai": "ความเป็นไปได้",
      "french": "possibilité",
      "chinese": "可能性",
      "chineseTraditional": "可能性",
      "partOfSpeech": "noun",
      "emoji": "🎲",
      "example": "비가 올 가능성이 높아요.",
      "exampleRomanization": "biga ol ganeungseongi nopayo.",
      "exampleTranslation": "There is a high chance of rain.",
      "timestamp": 192.5
    },
    {
      "korean": "추리",
      "romanization": "churi",
      "english": "deduction; reasoning",
      "spanish": "deducción; razonamiento",
      "portuguese": "dedução; raciocínio",
      "indonesian": "deduksi; penalaran",
      "japanese": "推理",
      "thai": "การอนุมาน; การสืบสวน",
      "french": "déduction; raisonnement",
      "chinese": "推理",
      "chineseTraditional": "推理",
      "partOfSpeech": "noun",
      "emoji": "🧩",
      "example": "그의 추리가 정확히 맞았어요.",
      "exampleRomanization": "geuui churiga jeonghwakhi majasseoyo.",
      "exampleTranslation": "His deduction was exactly right.",
      "timestamp": 195.96
    },
    {
      "korean": "인과응보",
      "romanization": "ingwaeungbo",
      "english": "karmic retribution; just deserts",
      "spanish": "karma; justicia poética",
      "portuguese": "carma; justiça poética",
      "indonesian": "karma; buah dari perbuatan",
      "japanese": "因果応報",
      "thai": "กรรมตามสนอง",
      "french": "juste retour des choses; karma",
      "chinese": "因果报应",
      "chineseTraditional": "因果報應",
      "partOfSpeech": "noun",
      "emoji": "☯️",
      "example": "이게 다 인과응보인 것 같아요.",
      "exampleRomanization": "ige da ingwaeungboin geot gatayo.",
      "exampleTranslation": "This all seems like karmic retribution.",
      "timestamp": 200.46
    },
    {
      "korean": "방법",
      "romanization": "bangbeop",
      "english": "method; way",
      "spanish": "método; manera",
      "portuguese": "método; maneira",
      "indonesian": "cara; metode",
      "japanese": "方法",
      "thai": "วิธี",
      "french": "méthode; manière",
      "chinese": "方法",
      "chineseTraditional": "方法",
      "partOfSpeech": "noun",
      "emoji": "🛠️",
      "example": "더 좋은 방법을 함께 찾아봐요.",
      "exampleRomanization": "deo joeun bangbeobeul hamkke chajabwayo.",
      "exampleTranslation": "Let's find a better way together.",
      "timestamp": 201.0
    },
    {
      "korean": "선물",
      "romanization": "seonmul",
      "english": "gift; present",
      "spanish": "regalo",
      "portuguese": "presente",
      "indonesian": "hadiah",
      "japanese": "プレゼント; 贈り物",
      "thai": "ของขวัญ",
      "french": "cadeau",
      "chinese": "礼物",
      "chineseTraditional": "禮物",
      "partOfSpeech": "noun",
      "emoji": "🎁",
      "example": "친구에게 작은 선물을 준비했어요.",
      "exampleRomanization": "chinguege jageun seonmureul junbihaesseoyo.",
      "exampleTranslation": "I prepared a small gift for my friend.",
      "timestamp": 242.36
    },
    {
      "korean": "형",
      "romanization": "hyeong",
      "english": "older brother (of a male)",
      "spanish": "hermano mayor",
      "portuguese": "irmão mais velho",
      "indonesian": "kakak laki-laki",
      "japanese": "兄",
      "thai": "พี่ชาย",
      "french": "grand frère",
      "chinese": "哥哥",
      "chineseTraditional": "哥哥",
      "partOfSpeech": "noun",
      "emoji": "👨",
      "example": "형이 나를 늘 챙겨 줘요.",
      "exampleRomanization": "hyeongi nareul neul chaenggyeo jwoyo.",
      "exampleTranslation": "My older brother always looks after me.",
      "timestamp": 254.0
    },
    {
      "korean": "나약하다",
      "romanization": "nayakhada",
      "english": "to be weak; feeble",
      "spanish": "ser débil",
      "portuguese": "ser fraco",
      "indonesian": "lemah",
      "japanese": "軟弱だ; 弱い",
      "thai": "อ่อนแอ",
      "french": "être faible",
      "chinese": "软弱",
      "chineseTraditional": "軟弱",
      "partOfSpeech": "adjective",
      "emoji": "🥀",
      "example": "그는 마음이 나약한 사람이 아니에요.",
      "exampleRomanization": "geuneun maeumi nayakhan sarami anieyo.",
      "exampleTranslation": "He is not a person of weak heart.",
      "timestamp": 254.36
    },
    {
      "korean": "맹세",
      "romanization": "maengse",
      "english": "oath; vow",
      "spanish": "juramento",
      "portuguese": "juramento",
      "indonesian": "sumpah",
      "japanese": "誓い",
      "thai": "คำสาบาน",
      "french": "serment",
      "chinese": "誓言；发誓",
      "chineseTraditional": "誓言；發誓",
      "partOfSpeech": "noun",
      "emoji": "🤚",
      "example": "그는 꼭 돌아오겠다고 맹세했어요.",
      "exampleRomanization": "geuneun kkok doraogetdago maengsehaesseoyo.",
      "exampleTranslation": "He vowed that he would surely come back.",
      "timestamp": 261.36
    },
    {
      "korean": "삶",
      "romanization": "sam",
      "english": "life",
      "spanish": "vida",
      "portuguese": "vida",
      "indonesian": "kehidupan; hidup",
      "japanese": "人生; 生活",
      "thai": "ชีวิต",
      "french": "vie",
      "chinese": "人生；生活",
      "chineseTraditional": "人生；生活",
      "partOfSpeech": "noun",
      "emoji": "🌱",
      "example": "그녀는 새로운 삶을 시작했어요.",
      "exampleRomanization": "geunyeoneun saeroun sameul sijakhaesseoyo.",
      "exampleTranslation": "She started a new life.",
      "timestamp": 264.36
    },
    {
      "korean": "여자",
      "romanization": "yeoja",
      "english": "woman",
      "spanish": "mujer",
      "portuguese": "mulher",
      "indonesian": "wanita; perempuan",
      "japanese": "女性",
      "thai": "ผู้หญิง",
      "french": "femme",
      "chinese": "女人",
      "chineseTraditional": "女人",
      "partOfSpeech": "noun",
      "emoji": "👩",
      "example": "저기 서 있는 여자는 제 친구예요.",
      "exampleRomanization": "jeogi seo inneun yeojaneun je chinguyeyo.",
      "exampleTranslation": "The woman standing over there is my friend.",
      "timestamp": 270.36
    },
    {
      "korean": "목",
      "romanization": "mok",
      "english": "neck; throat",
      "spanish": "cuello; garganta",
      "portuguese": "pescoço; garganta",
      "indonesian": "leher; tenggorokan",
      "japanese": "首; 喉",
      "thai": "คอ",
      "french": "cou; gorge",
      "chinese": "脖子；喉咙",
      "chineseTraditional": "脖子；喉嚨",
      "partOfSpeech": "noun",
      "emoji": "🧣",
      "example": "감기에 걸려서 목이 아파요.",
      "exampleRomanization": "gamgie geollyeoseo mogi apayo.",
      "exampleTranslation": "My throat hurts because I caught a cold.",
      "timestamp": 270.5
    },
    {
      "korean": "따라오다",
      "romanization": "ttaraoda",
      "english": "to follow; to come along",
      "spanish": "seguir; venir detrás",
      "portuguese": "seguir; vir atrás",
      "indonesian": "mengikuti; ikut",
      "japanese": "ついて来る",
      "thai": "ตามมา",
      "french": "suivre; venir derrière",
      "chinese": "跟着来；跟上",
      "chineseTraditional": "跟著來；跟上",
      "partOfSpeech": "verb",
      "emoji": "🐾",
      "example": "강아지가 나를 계속 따라와요.",
      "exampleRomanization": "gangajiga nareul gyesok ttarawayo.",
      "exampleTranslation": "The puppy keeps following me.",
      "timestamp": 280.36
    },
    {
      "korean": "곧",
      "romanization": "got",
      "english": "soon; shortly",
      "spanish": "pronto",
      "portuguese": "logo; em breve",
      "indonesian": "segera",
      "japanese": "すぐに; まもなく",
      "thai": "เร็ว ๆ นี้; อีกไม่นาน",
      "french": "bientôt",
      "chinese": "很快；马上",
      "chineseTraditional": "很快；馬上",
      "partOfSpeech": "adverb",
      "emoji": "⏱️",
      "example": "기차가 곧 도착할 거예요.",
      "exampleRomanization": "gichaga got dochakhal geoyeyo.",
      "exampleTranslation": "The train will arrive soon.",
      "timestamp": 283.36
    }
  ]
}