{
  "id": "crash-landing-ep12-3",
  "title": "Se-ri Recruits Su-chan",
  "drama": "Crash Landing on You",
  "youtubeId": "7IF1EEkAXZg",
  "episode": 12,
  "part": 3,
  "introOffset": 0,
  "words": [
    {
      "korean": "보험",
      "romanization": "boheom",
      "english": "insurance",
      "spanish": "seguro",
      "portuguese": "seguro",
      "indonesian": "asuransi",
      "japanese": "保険",
      "thai": "ประกัน",
      "french": "assurance",
      "chinese": "保险",
      "chineseTraditional": "保險",
      "partOfSpeech": "noun",
      "emoji": "📋",
      "example": "새로 자동차 보험에 가입했어요.",
      "exampleRomanization": "saero jadongcha boheome gaipaesseoyo.",
      "exampleTranslation": "I newly signed up for car insurance.",
      "timestamp": 0.5
    },
    {
      "korean": "담당자",
      "romanization": "damdangja",
      "english": "person in charge",
      "spanish": "encargado; responsable",
      "portuguese": "responsável; encarregado",
      "indonesian": "penanggung jawab",
      "japanese": "担当者",
      "thai": "ผู้รับผิดชอบ",
      "french": "responsable; personne en charge",
      "chinese": "负责人",
      "chineseTraditional": "負責人",
      "partOfSpeech": "noun",
      "emoji": "🧑‍💼",
      "example": "이 일의 담당자가 누구예요?",
      "exampleRomanization": "i irui damdangjaga nuguyeyo?",
      "exampleTranslation": "Who is the person in charge of this?",
      "timestamp": 2.0
    },
    {
      "korean": "청구",
      "romanization": "cheonggu",
      "english": "claim; billing; demand",
      "spanish": "reclamación; cobro",
      "portuguese": "cobrança; reivindicação",
      "indonesian": "penagihan; klaim",
      "japanese": "請求",
      "thai": "การเรียกร้อง; การเรียกเก็บเงิน",
      "french": "réclamation; facturation",
      "chinese": "索赔; 请求",
      "chineseTraditional": "索賠; 請求",
      "partOfSpeech": "noun",
      "emoji": "🧾",
      "example": "보험금 청구 서류를 제출했어요.",
      "exampleRomanization": "boheomgeum cheonggu seoryureul jechulhaesseoyo.",
      "exampleTranslation": "I submitted the insurance claim documents.",
      "timestamp": 20.0
    },
    {
      "korean": "예정",
      "romanization": "yejeong",
      "english": "schedule; plan (as planned)",
      "spanish": "previsto; programado",
      "portuguese": "previsto; agendado",
      "indonesian": "rencana; jadwal",
      "japanese": "予定",
      "thai": "กำหนดการ; ตามแผน",
      "french": "prévu; programmé",
      "chinese": "预定; 计划",
      "chineseTraditional": "預定; 計劃",
      "partOfSpeech": "noun",
      "emoji": "📅",
      "example": "회의는 예정대로 진행됩니다.",
      "exampleRomanization": "hoeuineun yejeongdaero jinhaengdoemnida.",
      "exampleTranslation": "The meeting will proceed as scheduled.",
      "timestamp": 21.0
    },
    {
      "korean": "감원",
      "romanization": "gamwon",
      "english": "staff cut; layoff",
      "spanish": "recorte de personal",
      "portuguese": "corte de pessoal; demissão",
      "indonesian": "pengurangan pegawai; PHK",
      "japanese": "人員削減",
      "thai": "การลดพนักงาน",
      "french": "réduction d'effectifs",
      "chinese": "裁员",
      "chineseTraditional": "裁員",
      "partOfSpeech": "noun",
      "emoji": "📉",
      "example": "회사가 어려워서 감원을 결정했어요.",
      "exampleRomanization": "hoesaga eoryeowoseo gamwoneul gyeoljeonghaesseoyo.",
      "exampleTranslation": "The company decided on layoffs because it was struggling.",
      "timestamp": 21.5
    },
    {
      "korean": "취소하다",
      "romanization": "chwisohada",
      "english": "to cancel",
      "spanish": "cancelar",
      "portuguese": "cancelar",
      "indonesian": "membatalkan",
      "japanese": "取り消す; キャンセルする",
      "thai": "ยกเลิก",
      "french": "annuler",
      "chinese": "取消",
      "chineseTraditional": "取消",
      "partOfSpeech": "verb",
      "emoji": "❌",
      "example": "예약을 하루 전에 취소했어요.",
      "exampleRomanization": "yeyageul haru jeone chwisohaesseoyo.",
      "exampleTranslation": "I canceled the reservation a day before.",
      "timestamp": 23.0
    },
    {
      "korean": "힘",
      "romanization": "him",
      "english": "strength; power",
      "spanish": "fuerza; poder",
      "portuguese": "força; poder",
      "indonesian": "kekuatan; tenaga",
      "japanese": "力",
      "thai": "พลัง; แรง",
      "french": "force; pouvoir",
      "chinese": "力量",
      "chineseTraditional": "力量",
      "partOfSpeech": "noun",
      "emoji": "💪",
      "example": "저는 그럴 힘이 없어요.",
      "exampleRomanization": "jeoneun geureol himi eopseoyo.",
      "exampleTranslation": "I don't have the power to do that.",
      "timestamp": 33.5
    },
    {
      "korean": "미안하다",
      "romanization": "mianhada",
      "english": "to be sorry",
      "spanish": "sentir lo; disculparse",
      "portuguese": "sentir muito; desculpar-se",
      "indonesian": "minta maaf",
      "japanese": "すまない; 申し訳ない",
      "thai": "ขอโทษ; รู้สึกผิด",
      "french": "être désolé",
      "chinese": "抱歉; 对不起",
      "chineseTraditional": "抱歉; 對不起",
      "partOfSpeech": "adjective",
      "emoji": "😞",
      "example": "약속을 못 지켜서 미안해요.",
      "exampleRomanization": "yaksogeul mot jikyeoseo mianhaeyo.",
      "exampleTranslation": "I'm sorry I couldn't keep my promise.",
      "timestamp": 37.5
    },
    {
      "korean": "확인하다",
      "romanization": "hwaginhada",
      "english": "to check; to confirm",
      "spanish": "confirmar; comprobar",
      "portuguese": "confirmar; verificar",
      "indonesian": "memeriksa; memastikan",
      "japanese": "確認する",
      "thai": "ตรวจสอบ; ยืนยัน",
      "french": "vérifier; confirmer",
      "chinese": "确认",
      "chineseTraditional": "確認",
      "partOfSpeech": "verb",
      "emoji": "✅",
      "example": "그동안의 기록을 하나하나 확인했어요.",
      "exampleRomanization": "geudonganui girogeul hanahana hwaginhaesseoyo.",
      "exampleTranslation": "I checked the records one by one.",
      "timestamp": 60.0
    },
    {
      "korean": "수색하다",
      "romanization": "susaekhada",
      "english": "to search; to comb through",
      "spanish": "rastrear; buscar",
      "portuguese": "vasculhar; buscar",
      "indonesian": "menyisir; mencari",
      "japanese": "捜索する",
      "thai": "ค้นหา; ตรวจค้น",
      "french": "fouiller; ratisser",
      "chinese": "搜索",
      "chineseTraditional": "搜索",
      "partOfSpeech": "verb",
      "emoji": "🔦",
      "example": "구조대가 산 전체를 수색했어요.",
      "exampleRomanization": "gujodaega san jeonchereul susaekhaesseoyo.",
      "exampleTranslation": "The rescue team searched the entire mountain.",
      "timestamp": 76.0
    },
    {
      "korean": "자료",
      "romanization": "jaryo",
      "english": "data; material; documents",
      "spanish": "datos; material",
      "portuguese": "dados; material",
      "indonesian": "data; materi",
      "japanese": "資料",
      "thai": "ข้อมูล; เอกสาร",
      "french": "données; documents",
      "chinese": "资料",
      "chineseTraditional": "資料",
      "partOfSpeech": "noun",
      "emoji": "📂",
      "example": "이 자료들을 좀 살펴봐 주세요.",
      "exampleRomanization": "i jaryodeureul jom salpyeobwa juseyo.",
      "exampleTranslation": "Please take a look at these materials.",
      "timestamp": 81.0
    },
    {
      "korean": "포기",
      "romanization": "pogi",
      "english": "giving up",
      "spanish": "rendición; abandono",
      "portuguese": "desistência",
      "indonesian": "menyerah",
      "japanese": "諦め",
      "thai": "การยอมแพ้",
      "french": "abandon; renoncement",
      "chinese": "放弃",
      "chineseTraditional": "放棄",
      "partOfSpeech": "noun",
      "emoji": "🏳️",
      "example": "아직 포기하기엔 일러요.",
      "exampleRomanization": "ajik pogihagien illeoyo.",
      "exampleTranslation": "It's too early to give up yet.",
      "timestamp": 82.5
    },
    {
      "korean": "무인도",
      "romanization": "muindo",
      "english": "uninhabited island",
      "spanish": "isla desierta",
      "portuguese": "ilha deserta",
      "indonesian": "pulau tak berpenghuni",
      "japanese": "無人島",
      "thai": "เกาะร้าง",
      "french": "île déserte",
      "chinese": "无人岛",
      "chineseTraditional": "無人島",
      "partOfSpeech": "noun",
      "emoji": "🏝️",
      "example": "서해에는 작은 무인도가 많아요.",
      "exampleRomanization": "seohaeeneun jageun muindoga manhayo.",
      "exampleTranslation": "There are many small uninhabited islands in the West Sea.",
      "timestamp": 84.0
    },
    {
      "korean": "일면식",
      "romanization": "ilmyeonsik",
      "english": "slight acquaintance; having met once",
      "spanish": "conocimiento superficial",
      "portuguese": "conhecimento superficial",
      "indonesian": "sekadar kenal; pernah bertemu sekali",
      "japanese": "一面識",
      "thai": "การรู้จักผิวเผิน",
      "french": "connaissance superficielle",
      "chinese": "一面之缘",
      "chineseTraditional": "一面之緣",
      "partOfSpeech": "noun",
      "emoji": "👥",
      "example": "우리는 일면식도 없는 사이였어요.",
      "exampleRomanization": "urineun ilmyeonsikdo eopneun saiyeosseoyo.",
      "exampleTranslation": "We were people who had never even met once.",
      "timestamp": 90.0
    },
    {
      "korean": "바라다",
      "romanization": "barada",
      "english": "to hope; to wish",
      "spanish": "esperar; desear",
      "portuguese": "esperar; desejar",
      "indonesian": "berharap",
      "japanese": "願う; 望む",
      "thai": "หวัง; ปรารถนา",
      "french": "espérer; souhaiter",
      "chinese": "希望; 盼望",
      "chineseTraditional": "希望; 盼望",
      "partOfSpeech": "verb",
      "emoji": "🌟",
      "example": "당신이 잘되길 진심으로 바라요.",
      "exampleRomanization": "dangsini jaldoegil jinsimeuro barayo.",
      "exampleTranslation": "I sincerely hope things go well for you.",
      "timestamp": 91.0
    },
    {
      "korean": "믿다",
      "romanization": "mitda",
      "english": "to believe; to trust",
      "spanish": "creer; confiar",
      "portuguese": "acreditar; confiar",
      "indonesian": "percaya",
      "japanese": "信じる",
      "thai": "เชื่อ; ไว้ใจ",
      "french": "croire; faire confiance",
      "chinese": "相信",
      "chineseTraditional": "相信",
      "partOfSpeech": "verb",
      "emoji": "🤞",
      "example": "저는 끝까지 당신을 믿었어요.",
      "exampleRomanization": "jeoneun kkeutkkaji dangsineul mideosseoyo.",
      "exampleTranslation": "I believed in you until the very end.",
      "timestamp": 92.0
    },
    {
      "korean": "평균",
      "romanization": "pyeonggyun",
      "english": "average",
      "spanish": "promedio",
      "portuguese": "média",
      "indonesian": "rata-rata",
      "japanese": "平均",
      "thai": "ค่าเฉลี่ย",
      "french": "moyenne",
      "chinese": "平均",
      "chineseTraditional": "平均",
      "partOfSpeech": "noun",
      "emoji": "📊",
      "example": "하루 평균 여덟 시간씩 잤어요.",
      "exampleRomanization": "haru pyeonggyun yeodeol siganssik jasseoyo.",
      "exampleTranslation": "I slept an average of eight hours a day.",
      "timestamp": 108.0
    },
    {
      "korean": "집착",
      "romanization": "jipchak",
      "english": "obsession; attachment",
      "spanish": "obsesión; apego",
      "portuguese": "obsessão; apego",
      "indonesian": "obsesi; kemelekatan",
      "japanese": "執着",
      "thai": "ความยึดติด; ความหมกมุ่น",
      "french": "obsession; attachement",
      "chinese": "执着; 执念",
      "chineseTraditional": "執著; 執念",
      "partOfSpeech": "noun",
      "emoji": "🎯",
      "example": "그런 집착 덕분에 결국 찾아냈어요.",
      "exampleRomanization": "geureon jipchak deokbune gyeolguk chajanaesseoyo.",
      "exampleTranslation": "Thanks to that obsession, I finally found it.",
      "timestamp": 126.0
    },
    {
      "korean": "목소리",
      "romanization": "moksori",
      "english": "voice",
      "spanish": "voz",
      "portuguese": "voz",
      "indonesian": "suara",
      "japanese": "声",
      "thai": "เสียง",
      "french": "voix",
      "chinese": "嗓音; 声音",
      "chineseTraditional": "嗓音; 聲音",
      "partOfSpeech": "noun",
      "emoji": "🎙️",
      "example": "전화기 너머로 익숙한 목소리가 들렸어요.",
      "exampleRomanization": "jeonhwagi neomeoro iksukhan moksoriga deullyeosseoyo.",
      "exampleTranslation": "A familiar voice came through the phone.",
      "timestamp": 128.0
    },
    {
      "korean": "기쁘다",
      "romanization": "gippeuda",
      "english": "to be glad; happy",
      "spanish": "estar contento; alegre",
      "portuguese": "estar feliz; contente",
      "indonesian": "gembira; senang",
      "japanese": "嬉しい",
      "thai": "ดีใจ",
      "french": "être joyeux; content",
      "chinese": "高兴; 开心",
      "chineseTraditional": "高興; 開心",
      "partOfSpeech": "adjective",
      "emoji": "😊",
      "example": "그 소식을 듣고 정말 기뻤어요.",
      "exampleRomanization": "geu sosigeul deutgo jeongmal gippeosseoyo.",
      "exampleTranslation": "I was really glad to hear that news.",
      "timestamp": 141.0
    },
    {
      "korean": "좋아하다",
      "romanization": "joahada",
      "english": "to like",
      "spanish": "gustar",
      "portuguese": "gostar",
      "indonesian": "menyukai",
      "japanese": "好きだ",
      "thai": "ชอบ",
      "french": "aimer; apprécier",
      "chinese": "喜欢",
      "chineseTraditional": "喜歡",
      "partOfSpeech": "verb",
      "emoji": "❤️",
      "example": "저는 그런 열정을 아주 좋아해요.",
      "exampleRomanization": "jeoneun geureon yeoljeongeul aju joahaeyo.",
      "exampleTranslation": "I really like that kind of passion.",
      "timestamp": 144.5
    },
    {
      "korean": "스카우트",
      "romanization": "seukauteu",
      "english": "to scout; to recruit",
      "spanish": "reclutar; fichar",
      "portuguese": "recrutar; contratar",
      "indonesian": "merekrut",
      "japanese": "スカウト",
      "thai": "ดึงตัว; ชักชวนร่วมงาน",
      "french": "recruter; débaucher",
      "chinese": "挖角; 招募",
      "chineseTraditional": "挖角; 招募",
      "partOfSpeech": "noun",
      "emoji": "🎯",
      "example": "제가 당신을 스카우트하고 싶어요.",
      "exampleRomanization": "jega dangsineul seukauteuhago sipeoyo.",
      "exampleTranslation": "I'd like to recruit you.",
      "timestamp": 147.0
    },
    {
      "korean": "인정받다",
      "romanization": "injeongbatda",
      "english": "to be recognized; acknowledged",
      "spanish": "ser reconocido",
      "portuguese": "ser reconhecido",
      "indonesian": "diakui; dihargai",
      "japanese": "認められる",
      "thai": "ได้รับการยอมรับ",
      "french": "être reconnu",
      "chinese": "受到认可",
      "chineseTraditional": "受到認可",
      "partOfSpeech": "verb",
      "emoji": "🏅",
      "example": "그는 회사에서 능력을 인정받고 있어요.",
      "exampleRomanization": "geuneun hoesaeseo neungnyeogeul injeongbatgo isseoyo.",
      "exampleTranslation": "He is recognized for his ability at the company.",
      "timestamp": 153.0
    },
    {
      "korean": "연봉",
      "romanization": "yeonbong",
      "english": "annual salary",
      "spanish": "salario anual",
      "portuguese": "salário anual",
      "indonesian": "gaji tahunan",
      "japanese": "年俸",
      "thai": "เงินเดือนต่อปี",
      "french": "salaire annuel",
      "chinese": "年薪",
      "chineseTraditional": "年薪",
      "partOfSpeech": "noun",
      "emoji": "💸",
      "example": "이직하면서 연봉이 크게 올랐어요.",
      "exampleRomanization": "ijikhamyeonseo yeonbongi keuge ollasseoyo.",
      "exampleTranslation": "My annual salary went up a lot when I changed jobs.",
      "timestamp": 161.0
    },
    {
      "korean": "인센티브",
      "romanization": "insentibeu",
      "english": "incentive; bonus",
      "spanish": "incentivo",
      "portuguese": "incentivo",
      "indonesian": "insentif",
      "japanese": "インセンティブ",
      "thai": "เงินจูงใจ; โบนัส",
      "french": "prime; incitation",
      "chinese": "奖励; 激励",
      "chineseTraditional": "獎勵; 激勵",
      "partOfSpeech": "noun",
      "emoji": "🎁",
      "example": "실적에 따라 인센티브를 드릴게요.",
      "exampleRomanization": "siljeoge ttara insentibeureul deurilgeyo.",
      "exampleTranslation": "I'll give you incentives based on performance.",
      "timestamp": 165.0
    },
    {
      "korean": "감사하다",
      "romanization": "gamsahada",
      "english": "to be grateful; to thank",
      "spanish": "agradecer",
      "portuguese": "agradecer",
      "indonesian": "berterima kasih",
      "japanese": "感謝する",
      "thai": "ขอบคุณ",
      "french": "remercier; être reconnaissant",
      "chinese": "感谢",
      "chineseTraditional": "感謝",
      "partOfSpeech": "verb",
      "emoji": "🙏",
      "example": "좋은 기회를 주셔서 감사합니다.",
      "exampleRomanization": "joeun gihoereul jusyeoseo gamsahamnida.",
      "exampleTranslation": "Thank you for giving me a good opportunity.",
      "timestamp": 171.0
    }
  ]
}