{
  "id": "queen-of-tears-ep15-7",
  "title": "A Prison Visit and a Promise",
  "drama": "Queen of Tears",
  "youtubeId": "HcVEPaGWvuI",
  "episode": 15,
  "part": 7,
  "introOffset": 0,
  "words": [
    {
      "korean": "앉다",
      "romanization": "anda",
      "english": "to sit",
      "spanish": "sentarse",
      "portuguese": "sentar-se",
      "indonesian": "duduk",
      "japanese": "座る",
      "thai": "นั่ง",
      "french": "s'asseoir",
      "chinese": "坐",
      "chineseTraditional": "坐",
      "partOfSpeech": "verb",
      "emoji": "🪑",
      "example": "여기 편하게 앉으세요.",
      "exampleRomanization": "yeogi pyeonhage anjeuseyo.",
      "exampleTranslation": "Please sit here comfortably.",
      "timestamp": 10.0
    },
    {
      "korean": "몸",
      "romanization": "mom",
      "english": "body; health",
      "spanish": "cuerpo; salud",
      "portuguese": "corpo; saúde",
      "indonesian": "tubuh; kondisi badan",
      "japanese": "体",
      "thai": "ร่างกาย; สุขภาพ",
      "french": "corps; santé",
      "chinese": "身体",
      "chineseTraditional": "身體",
      "partOfSpeech": "noun",
      "emoji": "🧍",
      "example": "요즘 몸은 좀 어때요?",
      "exampleRomanization": "yojeum momeun jom eottaeyo?",
      "exampleTranslation": "How is your health these days?",
      "timestamp": 20.0
    },
    {
      "korean": "괜찮다",
      "romanization": "gwaenchanta",
      "english": "to be okay; to be fine",
      "spanish": "estar bien",
      "portuguese": "estar bem",
      "indonesian": "tidak apa-apa; baik-baik saja",
      "japanese": "大丈夫だ",
      "thai": "ไม่เป็นไร; โอเค",
      "french": "aller bien; ça va",
      "chinese": "没关系；还好",
      "chineseTraditional": "沒關係；還好",
      "partOfSpeech": "adjective",
      "emoji": "🙆",
      "example": "걱정 마세요, 저는 괜찮아요.",
      "exampleRomanization": "geokjeong maseyo, jeoneun gwaenchanayo.",
      "exampleTranslation": "Don't worry, I'm okay.",
      "timestamp": 30.6
    },
    {
      "korean": "수술",
      "romanization": "susul",
      "english": "surgery; operation",
      "spanish": "cirugía; operación",
      "portuguese": "cirurgia; operação",
      "indonesian": "operasi",
      "japanese": "手術",
      "thai": "การผ่าตัด",
      "french": "opération; chirurgie",
      "chinese": "手术",
      "chineseTraditional": "手術",
      "partOfSpeech": "noun",
      "emoji": "🏥",
      "example": "수술은 무사히 잘 끝났어요.",
      "exampleRomanization": "susureun musahi jal kkeutnasseoyo.",
      "exampleTranslation": "The surgery ended safely and well.",
      "timestamp": 34.5
    },
    {
      "korean": "치료",
      "romanization": "chiryo",
      "english": "treatment; medical care",
      "spanish": "tratamiento",
      "portuguese": "tratamento",
      "indonesian": "pengobatan; perawatan",
      "japanese": "治療",
      "thai": "การรักษา",
      "french": "traitement; soins",
      "chinese": "治疗",
      "chineseTraditional": "治療",
      "partOfSpeech": "noun",
      "emoji": "💊",
      "example": "치료를 계속 받으면 나아질 거예요.",
      "exampleRomanization": "chiryoreul gyesok badeumyeon naajil geoyeyo.",
      "exampleTranslation": "If you keep getting treatment, you'll get better.",
      "timestamp": 36.0
    },
    {
      "korean": "걱정",
      "romanization": "geokjeong",
      "english": "worry; concern",
      "spanish": "preocupación",
      "portuguese": "preocupação",
      "indonesian": "kekhawatiran",
      "japanese": "心配",
      "thai": "ความกังวล",
      "french": "inquiétude; souci",
      "chinese": "担心；担忧",
      "chineseTraditional": "擔心；擔憂",
      "partOfSpeech": "noun",
      "emoji": "😟",
      "example": "그런 걱정은 하지 않아도 돼요.",
      "exampleRomanization": "geureon geokjeongeun haji anado dwaeyo.",
      "exampleTranslation": "You don't need to worry about that.",
      "timestamp": 39.7
    },
    {
      "korean": "웃기다",
      "romanization": "utgida",
      "english": "to be funny; to be absurd",
      "spanish": "ser gracioso; ser absurdo",
      "portuguese": "ser engraçado; ser absurdo",
      "indonesian": "lucu; menggelikan",
      "japanese": "おかしい; 笑わせる",
      "thai": "ตลก; น่าขัน",
      "french": "être drôle; être absurde",
      "chinese": "好笑；可笑",
      "chineseTraditional": "好笑；可笑",
      "partOfSpeech": "verb",
      "emoji": "🙃",
      "example": "그 변명은 정말 웃기네요.",
      "exampleRomanization": "geu byeonmyeongeun jeongmal utgineyo.",
      "exampleTranslation": "That excuse is really absurd.",
      "timestamp": 53.6
    },
    {
      "korean": "기억",
      "romanization": "gieok",
      "english": "memory",
      "spanish": "memoria; recuerdo",
      "portuguese": "memória; lembrança",
      "indonesian": "ingatan; kenangan",
      "japanese": "記憶",
      "thai": "ความทรงจำ",
      "french": "mémoire; souvenir",
      "chinese": "记忆",
      "chineseTraditional": "記憶",
      "partOfSpeech": "noun",
      "emoji": "🧠",
      "example": "그날의 기억이 아직 생생해요.",
      "exampleRomanization": "geunarui gieogi ajik saengsaenghaeyo.",
      "exampleTranslation": "The memory of that day is still vivid.",
      "timestamp": 55.6
    },
    {
      "korean": "알다",
      "romanization": "alda",
      "english": "to know",
      "spanish": "saber; conocer",
      "portuguese": "saber; conhecer",
      "indonesian": "tahu; mengetahui",
      "japanese": "知る; 分かる",
      "thai": "รู้; ทราบ",
      "french": "savoir; connaître",
      "chinese": "知道；了解",
      "chineseTraditional": "知道；了解",
      "partOfSpeech": "verb",
      "emoji": "💡",
      "example": "저는 이미 다 알고 있어요.",
      "exampleRomanization": "jeoneun imi da algo isseoyo.",
      "exampleTranslation": "I already know everything.",
      "timestamp": 66.6
    },
    {
      "korean": "목표",
      "romanization": "mokpyo",
      "english": "goal; objective",
      "spanish": "objetivo; meta",
      "portuguese": "objetivo; meta",
      "indonesian": "tujuan; sasaran",
      "japanese": "目標",
      "thai": "เป้าหมาย",
      "french": "objectif; but",
      "chinese": "目标",
      "chineseTraditional": "目標",
      "partOfSpeech": "noun",
      "emoji": "🎯",
      "example": "올해 목표를 꼭 이루고 싶어요.",
      "exampleRomanization": "olhae mokpyoreul kkok irugo sipeoyo.",
      "exampleTranslation": "I really want to reach this year's goal.",
      "timestamp": 68.6
    },
    {
      "korean": "이혼",
      "romanization": "ihon",
      "english": "divorce",
      "spanish": "divorcio",
      "portuguese": "divórcio",
      "indonesian": "perceraian",
      "japanese": "離婚",
      "thai": "การหย่าร้าง",
      "french": "divorce",
      "chinese": "离婚",
      "chineseTraditional": "離婚",
      "partOfSpeech": "noun",
      "emoji": "💔",
      "example": "두 사람은 결국 이혼을 했어요.",
      "exampleRomanization": "du sarameun gyeolguk ihoneul haesseoyo.",
      "exampleTranslation": "The two of them eventually got divorced.",
      "timestamp": 70.0
    },
    {
      "korean": "준비",
      "romanization": "junbi",
      "english": "preparation",
      "spanish": "preparación",
      "portuguese": "preparação",
      "indonesian": "persiapan",
      "japanese": "準備",
      "thai": "การเตรียมตัว",
      "french": "préparation",
      "chinese": "准备",
      "chineseTraditional": "準備",
      "partOfSpeech": "noun",
      "emoji": "📝",
      "example": "여행 준비는 다 끝났어요.",
      "exampleRomanization": "yeohaeng junbineun da kkeutnasseoyo.",
      "exampleTranslation": "The travel preparations are all done.",
      "timestamp": 72.0
    },
    {
      "korean": "확인하다",
      "romanization": "hwaginhada",
      "english": "to check; to confirm",
      "spanish": "comprobar; confirmar",
      "portuguese": "verificar; confirmar",
      "indonesian": "memastikan; mengecek",
      "japanese": "確認する",
      "thai": "ตรวจสอบ; ยืนยัน",
      "french": "vérifier; confirmer",
      "chinese": "确认；核实",
      "chineseTraditional": "確認；核實",
      "partOfSpeech": "verb",
      "emoji": "✔️",
      "example": "출발 전에 시간을 다시 확인했어요.",
      "exampleRomanization": "chulbal jeone siganeul dasi hwaginhaesseoyo.",
      "exampleTranslation": "I checked the time again before leaving.",
      "timestamp": 74.6
    },
    {
      "korean": "혼란스럽다",
      "romanization": "hollanseureopda",
      "english": "to be confused; chaotic",
      "spanish": "estar confundido",
      "portuguese": "estar confuso",
      "indonesian": "bingung; kacau",
      "japanese": "混乱している",
      "thai": "สับสน",
      "french": "être troublé; confus",
      "chinese": "混乱；困惑",
      "chineseTraditional": "混亂；困惑",
      "partOfSpeech": "adjective",
      "emoji": "😵",
      "example": "갑작스러운 소식에 마음이 혼란스러웠어요.",
      "exampleRomanization": "gapjakseureoun sosige maeumi hollanseureowosseoyo.",
      "exampleTranslation": "I felt confused by the sudden news.",
      "timestamp": 86.6
    },
    {
      "korean": "믿다",
      "romanization": "mitda",
      "english": "to believe; to trust",
      "spanish": "creer; confiar",
      "portuguese": "acreditar; confiar",
      "indonesian": "percaya",
      "japanese": "信じる",
      "thai": "เชื่อ; ไว้ใจ",
      "french": "croire; faire confiance",
      "chinese": "相信；信任",
      "chineseTraditional": "相信；信任",
      "partOfSpeech": "verb",
      "emoji": "🤞",
      "example": "저는 당신의 말을 믿어요.",
      "exampleRomanization": "jeoneun dangsinui mareul mideoyo.",
      "exampleTranslation": "I believe what you say.",
      "timestamp": 87.5
    },
    {
      "korean": "눈",
      "romanization": "nun",
      "english": "eye",
      "spanish": "ojo",
      "portuguese": "olho",
      "indonesian": "mata",
      "japanese": "目",
      "thai": "ตา; ดวงตา",
      "french": "œil",
      "chinese": "眼睛",
      "chineseTraditional": "眼睛",
      "partOfSpeech": "noun",
      "emoji": "👁️",
      "example": "저는 제 눈으로 직접 봤어요.",
      "exampleRomanization": "jeoneun je nuneuro jikjeop bwasseoyo.",
      "exampleTranslation": "I saw it with my own eyes.",
      "timestamp": 89.6
    },
    {
      "korean": "살인",
      "romanization": "sarin",
      "english": "murder; killing",
      "spanish": "asesinato",
      "portuguese": "assassinato; homicídio",
      "indonesian": "pembunuhan",
      "japanese": "殺人",
      "thai": "การฆาตกรรม",
      "french": "meurtre; homicide",
      "chinese": "杀人；谋杀",
      "chineseTraditional": "殺人；謀殺",
      "partOfSpeech": "noun",
      "emoji": "🔪",
      "example": "경찰이 그 살인 사건을 수사하고 있어요.",
      "exampleRomanization": "gyeongchari geu sarin sageoneul susahago isseoyo.",
      "exampleTranslation": "The police are investigating that murder case.",
      "timestamp": 91.6
    },
    {
      "korean": "용의자",
      "romanization": "yonguija",
      "english": "suspect",
      "spanish": "sospechoso",
      "portuguese": "suspeito",
      "indonesian": "tersangka",
      "japanese": "容疑者",
      "thai": "ผู้ต้องสงสัย",
      "french": "suspect",
      "chinese": "嫌疑人",
      "chineseTraditional": "嫌疑人",
      "partOfSpeech": "noun",
      "emoji": "🕵️",
      "example": "그는 사건의 유력한 용의자예요.",
      "exampleRomanization": "geuneun sageonui yuryeokhan yonguijayeyo.",
      "exampleTranslation": "He is a strong suspect in the case.",
      "timestamp": 92.5
    },
    {
      "korean": "만나다",
      "romanization": "mannada",
      "english": "to meet",
      "spanish": "encontrarse; ver a alguien",
      "portuguese": "encontrar-se",
      "indonesian": "bertemu",
      "japanese": "会う",
      "thai": "พบ; เจอ",
      "french": "rencontrer; voir",
      "chinese": "见面；遇见",
      "chineseTraditional": "見面；遇見",
      "partOfSpeech": "verb",
      "emoji": "🤝",
      "example": "우리는 언젠가 다시 만날 거예요.",
      "exampleRomanization": "urineun eonjenga dasi mannal geoyeyo.",
      "exampleTranslation": "We will meet again someday.",
      "timestamp": 119.6
    },
    {
      "korean": "솔직히",
      "romanization": "soljikhi",
      "english": "honestly; frankly",
      "spanish": "honestamente; francamente",
      "portuguese": "honestamente; francamente",
      "indonesian": "sejujurnya; terus terang",
      "japanese": "正直に",
      "thai": "พูดตามตรง",
      "french": "honnêtement; franchement",
      "chinese": "老实说；坦白说",
      "chineseTraditional": "老實說；坦白說",
      "partOfSpeech": "adverb",
      "emoji": "💯",
      "example": "솔직히 저도 조금 두려웠어요.",
      "exampleRomanization": "soljikhi jeodo jogeum duryeowosseoyo.",
      "exampleTranslation": "Honestly, I was a little scared too.",
      "timestamp": 125.6
    },
    {
      "korean": "궁금하다",
      "romanization": "gunggeumhada",
      "english": "to be curious",
      "spanish": "tener curiosidad",
      "portuguese": "estar curioso",
      "indonesian": "penasaran",
      "japanese": "気になる",
      "thai": "อยากรู้; สงสัย",
      "french": "être curieux",
      "chinese": "好奇；想知道",
      "chineseTraditional": "好奇；想知道",
      "partOfSpeech": "adjective",
      "emoji": "🤔",
      "example": "결과가 정말 궁금해요.",
      "exampleRomanization": "gyeolgwaga jeongmal gunggeumhaeyo.",
      "exampleTranslation": "I'm really curious about the result.",
      "timestamp": 126.0
    },
    {
      "korean": "평생",
      "romanization": "pyeongsaeng",
      "english": "whole life; lifetime",
      "spanish": "toda la vida",
      "portuguese": "vida inteira",
      "indonesian": "seumur hidup",
      "japanese": "一生",
      "thai": "ตลอดชีวิต",
      "french": "toute la vie",
      "chinese": "一辈子；一生",
      "chineseTraditional": "一輩子；一生",
      "partOfSpeech": "noun",
      "emoji": "♾️",
      "example": "이 순간을 평생 잊지 못할 거예요.",
      "exampleRomanization": "i sunganeul pyeongsaeng itji mothal geoyeyo.",
      "exampleTranslation": "I will never forget this moment my whole life.",
      "timestamp": 127.6
    },
    {
      "korean": "지치다",
      "romanization": "jichida",
      "english": "to get tired; to be worn out",
      "spanish": "cansarse; agotarse",
      "portuguese": "cansar-se; esgotar-se",
      "indonesian": "lelah; kepayahan",
      "japanese": "疲れる; くたびれる",
      "thai": "เหนื่อยล้า; หมดแรง",
      "french": "s'épuiser; être las",
      "chinese": "疲惫；厌倦",
      "chineseTraditional": "疲憊；厭倦",
      "partOfSpeech": "verb",
      "emoji": "😩",
      "example": "저는 절대 지치지 않을 거예요.",
      "exampleRomanization": "jeoneun jeoldae jichiji aneul geoyeyo.",
      "exampleTranslation": "I will never get tired.",
      "timestamp": 137.1
    },
    {
      "korean": "옆",
      "romanization": "yeop",
      "english": "side; next to",
      "spanish": "al lado",
      "portuguese": "ao lado",
      "indonesian": "sebelah; di samping",
      "japanese": "隣; 横",
      "thai": "ข้างๆ",
      "french": "à côté",
      "chinese": "旁边",
      "chineseTraditional": "旁邊",
      "partOfSpeech": "noun",
      "emoji": "↔️",
      "example": "제 옆에 앉아도 돼요.",
      "exampleRomanization": "je yeope anjado dwaeyo.",
      "exampleTranslation": "You can sit next to me.",
      "timestamp": 138.0
    },
    {
      "korean": "자신감",
      "romanization": "jasingam",
      "english": "confidence; self-assurance",
      "spanish": "confianza en uno mismo",
      "portuguese": "autoconfiança",
      "indonesian": "rasa percaya diri",
      "japanese": "自信",
      "thai": "ความมั่นใจ",
      "french": "confiance en soi",
      "chinese": "自信",
      "chineseTraditional": "自信",
      "partOfSpeech": "noun",
      "emoji": "😤",
      "example": "그는 자신감이 넘치는 사람이에요.",
      "exampleRomanization": "geuneun jasingami neomchineun saramieyo.",
      "exampleTranslation": "He is a person full of confidence.",
      "timestamp": 141.9
    },
    {
      "korean": "약속하다",
      "romanization": "yaksokhada",
      "english": "to promise",
      "spanish": "prometer",
      "portuguese": "prometer",
      "indonesian": "berjanji",
      "japanese": "約束する",
      "thai": "สัญญา",
      "french": "promettre",
      "chinese": "约定；承诺",
      "chineseTraditional": "約定；承諾",
      "partOfSpeech": "verb",
      "emoji": "🤙",
      "example": "다시 오겠다고 약속했어요.",
      "exampleRomanization": "dasi ogetdago yaksokhaesseoyo.",
      "exampleTranslation": "I promised that I would come again.",
      "timestamp": 159.7
    },
    {
      "korean": "혼자",
      "romanization": "honja",
      "english": "alone; by oneself",
      "spanish": "solo",
      "portuguese": "sozinho",
      "indonesian": "sendirian",
      "japanese": "一人で",
      "thai": "คนเดียว; ลำพัง",
      "french": "seul",
      "chinese": "独自；一个人",
      "chineseTraditional": "獨自；一個人",
      "partOfSpeech": "adverb",
      "emoji": "🚶",
      "example": "저는 혼자 여행하는 걸 좋아해요.",
      "exampleRomanization": "jeoneun honja yeohaenghaneun geol joahaeyo.",
      "exampleTranslation": "I like traveling alone.",
      "timestamp": 170.7
    },
    {
      "korean": "나가다",
      "romanization": "nagada",
      "english": "to go out; to get out",
      "spanish": "salir",
      "portuguese": "sair",
      "indonesian": "keluar",
      "japanese": "出る; 出て行く",
      "thai": "ออกไป",
      "french": "sortir",
      "chinese": "出去",
      "chineseTraditional": "出去",
      "partOfSpeech": "verb",
      "emoji": "🚪",
      "example": "잠깐 밖에 나갔다 올게요.",
      "exampleRomanization": "jamkkan bakke nagatda olgeyo.",
      "exampleTranslation": "I'll step outside for a moment and come back.",
      "timestamp": 179.7
    },
    {
      "korean": "지키다",
      "romanization": "jikida",
      "english": "to keep; to protect",
      "spanish": "cumplir; proteger",
      "portuguese": "cumprir; proteger",
      "indonesian": "menepati; melindungi",
      "japanese": "守る",
      "thai": "รักษา; ปกป้อง",
      "french": "tenir (une promesse); protéger",
      "chinese": "遵守；守护",
      "chineseTraditional": "遵守；守護",
      "partOfSpeech": "verb",
      "emoji": "🛡️",
      "example": "약속은 반드시 지킬게요.",
      "exampleRomanization": "yaksogeun bandeusi jikilgeyo.",
      "exampleTranslation": "I will definitely keep my promise.",
      "timestamp": 182.7
    },
    {
      "korean": "건강하다",
      "romanization": "geonganghada",
      "english": "to be healthy",
      "spanish": "estar sano; ser saludable",
      "portuguese": "ser saudável",
      "indonesian": "sehat",
      "japanese": "健康だ",
      "thai": "สุขภาพดี; แข็งแรง",
      "french": "être en bonne santé",
      "chinese": "健康",
      "chineseTraditional": "健康",
      "partOfSpeech": "adjective",
      "emoji": "💪",
      "example": "부디 건강하게 지내세요.",
      "exampleRomanization": "budi geonganghage jinaeseyo.",
      "exampleTranslation": "Please stay healthy.",
      "timestamp": 197.7
    },
    {
      "korean": "감사하다",
      "romanization": "gamsahada",
      "english": "to be thankful; to thank",
      "spanish": "agradecer",
      "portuguese": "agradecer",
      "indonesian": "berterima kasih",
      "japanese": "感謝する",
      "thai": "ขอบคุณ",
      "french": "remercier",
      "chinese": "感谢",
      "chineseTraditional": "感謝",
      "partOfSpeech": "verb",
      "emoji": "🙇",
      "example": "와 주셔서 감사합니다.",
      "exampleRomanization": "wa jusyeoseo gamsahamnida.",
      "exampleTranslation": "Thank you for coming.",
      "timestamp": 216.7
    }
  ]
}